fastqTomat0/__init__.py
fastqTomat0/atac_pipeline.py
fastqTomat0/fastqBCLinker.py
fastqTomat0/fastqBCLinkerv31.py
fastqTomat0/fastqForce10xBarcodes.py
fastqTomat0/fastqUMICount.py
fastqTomat0/gffAnnotate.py
fastqTomat0/makeNoiseOnlyExpression.py
fastqTomat0/readSudoku.py
fastqTomat0/shift_reads.py
fastqTomat0/tenXtomatrix.py
fastqTomat0/trim_ref_polyA.py
fastqTomat0/processor/__init__.py
fastqTomat0/processor/barcode_indexer.py
fastqTomat0/processor/degenerate_tools.py
fastqTomat0/processor/fasta.py
fastqTomat0/processor/fastq.py
fastqTomat0/processor/gff.py
fastqTomat0/processor/steinmetz.py
fastqTomat0/processor/tenX.py
fastqTomat0-0.1.0.dist-info/LICENSE
fastqTomat0-0.1.0.dist-info/METADATA
fastqTomat0-0.1.0.dist-info/WHEEL
fastqTomat0-0.1.0.dist-info/top_level.txt
fastqTomat0-0.1.0.dist-info/RECORD
